fastplotlib/__init__.py
fastplotlib/_version.py
fastplotlib/assets/egg.gif
fastplotlib/assets/fastplotlib_face_logo.png
fastplotlib/graphics/__init__.py
fastplotlib/graphics/_axes.py
fastplotlib/graphics/_base.py
fastplotlib/graphics/_collection_base.py
fastplotlib/graphics/_positions_base.py
fastplotlib/graphics/image.py
fastplotlib/graphics/image_volume.py
fastplotlib/graphics/line.py
fastplotlib/graphics/line_collection.py
fastplotlib/graphics/scatter.py
fastplotlib/graphics/text.py
fastplotlib/graphics/utils.py
fastplotlib/graphics/features/__init__.py
fastplotlib/graphics/features/_base.py
fastplotlib/graphics/features/_common.py
fastplotlib/graphics/features/_image.py
fastplotlib/graphics/features/_positions_graphics.py
fastplotlib/graphics/features/_selection_features.py
fastplotlib/graphics/features/_text.py
fastplotlib/graphics/features/_volume.py
fastplotlib/graphics/features/utils.py
fastplotlib/graphics/selectors/__init__.py
fastplotlib/graphics/selectors/_base_selector.py
fastplotlib/graphics/selectors/_linear.py
fastplotlib/graphics/selectors/_linear_region.py
fastplotlib/graphics/selectors/_polygon.py
fastplotlib/graphics/selectors/_rectangle.py
fastplotlib/layouts/__init__.py
fastplotlib/layouts/_engine.py
fastplotlib/layouts/_figure.py
fastplotlib/layouts/_frame.py
fastplotlib/layouts/_graphic_methods_mixin.py
fastplotlib/layouts/_imgui_figure.py
fastplotlib/layouts/_plot_area.py
fastplotlib/layouts/_rect.py
fastplotlib/layouts/_subplot.py
fastplotlib/layouts/_utils.py
fastplotlib/legends/__init__.py
fastplotlib/legends/legend.py
fastplotlib/tools/__init__.py
fastplotlib/tools/_histogram_lut.py
fastplotlib/tools/_tooltip.py
fastplotlib/ui/__init__.py
fastplotlib/ui/_base.py
fastplotlib/ui/_subplot_toolbar.py
fastplotlib/ui/right_click_menus/__init__.py
fastplotlib/ui/right_click_menus/_colormap_picker.py
fastplotlib/ui/right_click_menus/_standard_menu.py
fastplotlib/utils/__init__.py
fastplotlib/utils/_plot_helpers.py
fastplotlib/utils/enums.py
mbo_fpl-0.5.2.dist-info/licenses/LICENSE
mbo_fpl-0.5.2.dist-info/WHEEL
mbo_fpl-0.5.2.dist-info/METADATA
mbo_fpl-0.5.2.dist-info/RECORD
